{"nodes": [{"id": "modules_shadow_chain_of_thought_py", "label": "chain_of_thought.py", "file_type": "code", "source_file": "modules\\shadow\\chain_of_thought.py", "source_location": "L1"}, {"id": "chain_of_thought_reasoningstep", "label": "ReasoningStep", "file_type": "code", "source_file": "modules\\shadow\\chain_of_thought.py", "source_location": "L46"}, {"id": "chain_of_thought_chainresult", "label": "ChainResult", "file_type": "code", "source_file": "modules\\shadow\\chain_of_thought.py", "source_location": "L59"}, {"id": "chain_of_thought_chainofthought", "label": "ChainOfThought", "file_type": "code", "source_file": "modules\\shadow\\chain_of_thought.py", "source_location": "L70"}, {"id": "chain_of_thought_chainofthought_init", "label": ".__init__()", "file_type": "code", "source_file": "modules\\shadow\\chain_of_thought.py", "source_location": "L80"}, {"id": "chain_of_thought_chainofthought_reason", "label": ".reason()", "file_type": "code", "source_file": "modules\\shadow\\chain_of_thought.py", "source_location": "L97"}, {"id": "chain_of_thought_chainofthought_reason_custom", "label": ".reason_custom()", "file_type": "code", "source_file": "modules\\shadow\\chain_of_thought.py", "source_location": "L131"}, {"id": "chain_of_thought_chainofthought_estimate_complexity", "label": ".estimate_complexity()", "file_type": "code", "source_file": "modules\\shadow\\chain_of_thought.py", "source_location": "L172"}, {"id": "chain_of_thought_chainofthought_get_reasoning_stats", "label": ".get_reasoning_stats()", "file_type": "code", "source_file": "modules\\shadow\\chain_of_thought.py", "source_location": "L204"}, {"id": "chain_of_thought_chainofthought_build_simple_steps", "label": "._build_simple_steps()", "file_type": "code", "source_file": "modules\\shadow\\chain_of_thought.py", "source_location": "L249"}, {"id": "chain_of_thought_chainofthought_build_moderate_steps", "label": "._build_moderate_steps()", "file_type": "code", "source_file": "modules\\shadow\\chain_of_thought.py", "source_location": "L263"}, {"id": "chain_of_thought_chainofthought_build_complex_steps", "label": "._build_complex_steps()", "file_type": "code", "source_file": "modules\\shadow\\chain_of_thought.py", "source_location": "L298"}, {"id": "chain_of_thought_chainofthought_execute_pipeline", "label": "._execute_pipeline()", "file_type": "code", "source_file": "modules\\shadow\\chain_of_thought.py", "source_location": "L364"}, {"id": "chain_of_thought_estimate_tokens", "label": "_estimate_tokens()", "file_type": "code", "source_file": "modules\\shadow\\chain_of_thought.py", "source_location": "L462"}, {"id": "chain_of_thought_rationale_1", "label": "Chain-of-Thought Scaffolding \u2014 Structured Multi-Step Reasoning =================", "file_type": "rationale", "source_file": "modules\\shadow\\chain_of_thought.py", "source_location": "L1"}, {"id": "chain_of_thought_rationale_47", "label": "A single step in the chain-of-thought pipeline.", "file_type": "rationale", "source_file": "modules\\shadow\\chain_of_thought.py", "source_location": "L47"}, {"id": "chain_of_thought_rationale_60", "label": "Complete result of a chain-of-thought reasoning pass.", "file_type": "rationale", "source_file": "modules\\shadow\\chain_of_thought.py", "source_location": "L60"}, {"id": "chain_of_thought_rationale_71", "label": "Break complex reasoning into explicit sequential steps.      Each step is a SEPA", "file_type": "rationale", "source_file": "modules\\shadow\\chain_of_thought.py", "source_location": "L71"}, {"id": "chain_of_thought_rationale_85", "label": "Initialize the chain-of-thought scaffolding.          Args:             generate", "file_type": "rationale", "source_file": "modules\\shadow\\chain_of_thought.py", "source_location": "L85"}, {"id": "chain_of_thought_rationale_103", "label": "Main entry point for chain-of-thought reasoning.          Args:             task", "file_type": "rationale", "source_file": "modules\\shadow\\chain_of_thought.py", "source_location": "L103"}, {"id": "chain_of_thought_rationale_137", "label": "Run a custom step pipeline for domain-specific reasoning.          Args:", "file_type": "rationale", "source_file": "modules\\shadow\\chain_of_thought.py", "source_location": "L137"}, {"id": "chain_of_thought_rationale_173", "label": "Estimate task complexity from text characteristics.          Args:             t", "file_type": "rationale", "source_file": "modules\\shadow\\chain_of_thought.py", "source_location": "L173"}, {"id": "chain_of_thought_rationale_205", "label": "Return statistics from reasoning history.          Returns:             Dict wit", "file_type": "rationale", "source_file": "modules\\shadow\\chain_of_thought.py", "source_location": "L205"}, {"id": "chain_of_thought_rationale_250", "label": "Build a 1-step pipeline (direct attempt).", "file_type": "rationale", "source_file": "modules\\shadow\\chain_of_thought.py", "source_location": "L250"}, {"id": "chain_of_thought_rationale_264", "label": "Build a 2-step pipeline (understand + execute).", "file_type": "rationale", "source_file": "modules\\shadow\\chain_of_thought.py", "source_location": "L264"}, {"id": "chain_of_thought_rationale_299", "label": "Build the full 4-step pipeline.", "file_type": "rationale", "source_file": "modules\\shadow\\chain_of_thought.py", "source_location": "L299"}, {"id": "chain_of_thought_rationale_369", "label": "Execute a sequence of reasoning steps.          Each step is a separate model ca", "file_type": "rationale", "source_file": "modules\\shadow\\chain_of_thought.py", "source_location": "L369"}, {"id": "chain_of_thought_rationale_463", "label": "Rough token estimate: ~4 chars per token.", "file_type": "rationale", "source_file": "modules\\shadow\\chain_of_thought.py", "source_location": "L463"}], "edges": [{"source": "modules_shadow_chain_of_thought_py", "target": "logging", "relation": "imports", "confidence": "EXTRACTED", "source_file": "modules\\shadow\\chain_of_thought.py", "source_location": "L22", "weight": 1.0}, {"source": "modules_shadow_chain_of_thought_py", "target": "re", "relation": "imports", "confidence": "EXTRACTED", "source_file": "modules\\shadow\\chain_of_thought.py", "source_location": "L23", "weight": 1.0}, {"source": "modules_shadow_chain_of_thought_py", "target": "time", "relation": "imports", "confidence": "EXTRACTED", "source_file": "modules\\shadow\\chain_of_thought.py", "source_location": "L24", "weight": 1.0}, {"source": "modules_shadow_chain_of_thought_py", "target": "dataclasses", "relation": "imports_from", "confidence": "EXTRACTED", "source_file": "modules\\shadow\\chain_of_thought.py", "source_location": "L25", "weight": 1.0}, {"source": "modules_shadow_chain_of_thought_py", "target": "typing", "relation": "imports_from", "confidence": "EXTRACTED", "source_file": "modules\\shadow\\chain_of_thought.py", "source_location": "L26", "weight": 1.0}, {"source": "modules_shadow_chain_of_thought_py", "target": "chain_of_thought_reasoningstep", "relation": "contains", "confidence": "EXTRACTED", "source_file": "modules\\shadow\\chain_of_thought.py", "source_location": "L46", "weight": 1.0}, {"source": "modules_shadow_chain_of_thought_py", "target": "chain_of_thought_chainresult", "relation": "contains", "confidence": "EXTRACTED", "source_file": "modules\\shadow\\chain_of_thought.py", "source_location": "L59", "weight": 1.0}, {"source": "modules_shadow_chain_of_thought_py", "target": "chain_of_thought_chainofthought", "relation": "contains", "confidence": "EXTRACTED", "source_file": "modules\\shadow\\chain_of_thought.py", "source_location": "L70", "weight": 1.0}, {"source": "chain_of_thought_chainofthought", "target": "chain_of_thought_chainofthought_init", "relation": "method", "confidence": "EXTRACTED", "source_file": "modules\\shadow\\chain_of_thought.py", "source_location": "L80", "weight": 1.0}, {"source": "chain_of_thought_chainofthought", "target": "chain_of_thought_chainofthought_reason", "relation": "method", "confidence": "EXTRACTED", "source_file": "modules\\shadow\\chain_of_thought.py", "source_location": "L97", "weight": 1.0}, {"source": "chain_of_thought_chainofthought", "target": "chain_of_thought_chainofthought_reason_custom", "relation": "method", "confidence": "EXTRACTED", "source_file": "modules\\shadow\\chain_of_thought.py", "source_location": "L131", "weight": 1.0}, {"source": "chain_of_thought_chainofthought", "target": "chain_of_thought_chainofthought_estimate_complexity", "relation": "method", "confidence": "EXTRACTED", "source_file": "modules\\shadow\\chain_of_thought.py", "source_location": "L172", "weight": 1.0}, {"source": "chain_of_thought_chainofthought", "target": "chain_of_thought_chainofthought_get_reasoning_stats", "relation": "method", "confidence": "EXTRACTED", "source_file": "modules\\shadow\\chain_of_thought.py", "source_location": "L204", "weight": 1.0}, {"source": "chain_of_thought_chainofthought", "target": "chain_of_thought_chainofthought_build_simple_steps", "relation": "method", "confidence": "EXTRACTED", "source_file": "modules\\shadow\\chain_of_thought.py", "source_location": "L249", "weight": 1.0}, {"source": "chain_of_thought_chainofthought", "target": "chain_of_thought_chainofthought_build_moderate_steps", "relation": "method", "confidence": "EXTRACTED", "source_file": "modules\\shadow\\chain_of_thought.py", "source_location": "L263", "weight": 1.0}, {"source": "chain_of_thought_chainofthought", "target": "chain_of_thought_chainofthought_build_complex_steps", "relation": "method", "confidence": "EXTRACTED", "source_file": "modules\\shadow\\chain_of_thought.py", "source_location": "L298", "weight": 1.0}, {"source": "chain_of_thought_chainofthought", "target": "chain_of_thought_chainofthought_execute_pipeline", "relation": "method", "confidence": "EXTRACTED", "source_file": "modules\\shadow\\chain_of_thought.py", "source_location": "L364", "weight": 1.0}, {"source": "modules_shadow_chain_of_thought_py", "target": "chain_of_thought_estimate_tokens", "relation": "contains", "confidence": "EXTRACTED", "source_file": "modules\\shadow\\chain_of_thought.py", "source_location": "L462", "weight": 1.0}, {"source": "chain_of_thought_chainofthought_reason", "target": "chain_of_thought_chainresult", "relation": "calls", "confidence": "EXTRACTED", "source_file": "modules\\shadow\\chain_of_thought.py", "source_location": "L114", "weight": 1.0}, {"source": "chain_of_thought_chainofthought_reason", "target": "chain_of_thought_chainofthought_estimate_complexity", "relation": "calls", "confidence": "EXTRACTED", "source_file": "modules\\shadow\\chain_of_thought.py", "source_location": "L120", "weight": 1.0}, {"source": "chain_of_thought_chainofthought_reason", "target": "chain_of_thought_chainofthought_build_simple_steps", "relation": "calls", "confidence": "EXTRACTED", "source_file": "modules\\shadow\\chain_of_thought.py", "source_location": "L123", "weight": 1.0}, {"source": "chain_of_thought_chainofthought_reason", "target": "chain_of_thought_chainofthought_build_moderate_steps", "relation": "calls", "confidence": "EXTRACTED", "source_file": "modules\\shadow\\chain_of_thought.py", "source_location": "L125", "weight": 1.0}, {"source": "chain_of_thought_chainofthought_reason", "target": "chain_of_thought_chainofthought_build_complex_steps", "relation": "calls", "confidence": "EXTRACTED", "source_file": "modules\\shadow\\chain_of_thought.py", "source_location": "L127", "weight": 1.0}, {"source": "chain_of_thought_chainofthought_reason", "target": "chain_of_thought_chainofthought_execute_pipeline", "relation": "calls", "confidence": "EXTRACTED", "source_file": "modules\\shadow\\chain_of_thought.py", "source_location": "L129", "weight": 1.0}, {"source": "chain_of_thought_chainofthought_reason_custom", "target": "chain_of_thought_chainresult", "relation": "calls", "confidence": "EXTRACTED", "source_file": "modules\\shadow\\chain_of_thought.py", "source_location": "L149", "weight": 1.0}, {"source": "chain_of_thought_chainofthought_reason_custom", "target": "chain_of_thought_chainofthought_execute_pipeline", "relation": "calls", "confidence": "EXTRACTED", "source_file": "modules\\shadow\\chain_of_thought.py", "source_location": "L170", "weight": 1.0}, {"source": "chain_of_thought_chainofthought_execute_pipeline", "target": "chain_of_thought_chainresult", "relation": "calls", "confidence": "EXTRACTED", "source_file": "modules\\shadow\\chain_of_thought.py", "source_location": "L374", "weight": 1.0}, {"source": "chain_of_thought_chainofthought_execute_pipeline", "target": "chain_of_thought_reasoningstep", "relation": "calls", "confidence": "EXTRACTED", "source_file": "modules\\shadow\\chain_of_thought.py", "source_location": "L402", "weight": 1.0}, {"source": "chain_of_thought_chainofthought_execute_pipeline", "target": "chain_of_thought_estimate_tokens", "relation": "calls", "confidence": "EXTRACTED", "source_file": "modules\\shadow\\chain_of_thought.py", "source_location": "L409", "weight": 1.0}, {"source": "chain_of_thought_rationale_1", "target": "modules_shadow_chain_of_thought_py", "relation": "rationale_for", "confidence": "EXTRACTED", "source_file": "modules\\shadow\\chain_of_thought.py", "source_location": "L1", "weight": 1.0}, {"source": "chain_of_thought_rationale_47", "target": "chain_of_thought_reasoningstep", "relation": "rationale_for", "confidence": "EXTRACTED", "source_file": "modules\\shadow\\chain_of_thought.py", "source_location": "L47", "weight": 1.0}, {"source": "chain_of_thought_rationale_60", "target": "chain_of_thought_chainresult", "relation": "rationale_for", "confidence": "EXTRACTED", "source_file": "modules\\shadow\\chain_of_thought.py", "source_location": "L60", "weight": 1.0}, {"source": "chain_of_thought_rationale_71", "target": "chain_of_thought_chainofthought", "relation": "rationale_for", "confidence": "EXTRACTED", "source_file": "modules\\shadow\\chain_of_thought.py", "source_location": "L71", "weight": 1.0}, {"source": "chain_of_thought_rationale_85", "target": "chain_of_thought_chainofthought_init", "relation": "rationale_for", "confidence": "EXTRACTED", "source_file": "modules\\shadow\\chain_of_thought.py", "source_location": "L85", "weight": 1.0}, {"source": "chain_of_thought_rationale_103", "target": "chain_of_thought_chainofthought_reason", "relation": "rationale_for", "confidence": "EXTRACTED", "source_file": "modules\\shadow\\chain_of_thought.py", "source_location": "L103", "weight": 1.0}, {"source": "chain_of_thought_rationale_137", "target": "chain_of_thought_chainofthought_reason_custom", "relation": "rationale_for", "confidence": "EXTRACTED", "source_file": "modules\\shadow\\chain_of_thought.py", "source_location": "L137", "weight": 1.0}, {"source": "chain_of_thought_rationale_173", "target": "chain_of_thought_chainofthought_estimate_complexity", "relation": "rationale_for", "confidence": "EXTRACTED", "source_file": "modules\\shadow\\chain_of_thought.py", "source_location": "L173", "weight": 1.0}, {"source": "chain_of_thought_rationale_205", "target": "chain_of_thought_chainofthought_get_reasoning_stats", "relation": "rationale_for", "confidence": "EXTRACTED", "source_file": "modules\\shadow\\chain_of_thought.py", "source_location": "L205", "weight": 1.0}, {"source": "chain_of_thought_rationale_250", "target": "chain_of_thought_chainofthought_build_simple_steps", "relation": "rationale_for", "confidence": "EXTRACTED", "source_file": "modules\\shadow\\chain_of_thought.py", "source_location": "L250", "weight": 1.0}, {"source": "chain_of_thought_rationale_264", "target": "chain_of_thought_chainofthought_build_moderate_steps", "relation": "rationale_for", "confidence": "EXTRACTED", "source_file": "modules\\shadow\\chain_of_thought.py", "source_location": "L264", "weight": 1.0}, {"source": "chain_of_thought_rationale_299", "target": "chain_of_thought_chainofthought_build_complex_steps", "relation": "rationale_for", "confidence": "EXTRACTED", "source_file": "modules\\shadow\\chain_of_thought.py", "source_location": "L299", "weight": 1.0}, {"source": "chain_of_thought_rationale_369", "target": "chain_of_thought_chainofthought_execute_pipeline", "relation": "rationale_for", "confidence": "EXTRACTED", "source_file": "modules\\shadow\\chain_of_thought.py", "source_location": "L369", "weight": 1.0}, {"source": "chain_of_thought_rationale_463", "target": "chain_of_thought_chainofthought_estimate_tokens", "relation": "rationale_for", "confidence": "EXTRACTED", "source_file": "modules\\shadow\\chain_of_thought.py", "source_location": "L463", "weight": 1.0}], "raw_calls": [{"caller_nid": "chain_of_thought_chainofthought_reason", "callee": "append", "source_file": "modules\\shadow\\chain_of_thought.py", "source_location": "L116"}, {"caller_nid": "chain_of_thought_chainofthought_reason_custom", "callee": "append", "source_file": "modules\\shadow\\chain_of_thought.py", "source_location": "L151"}, {"caller_nid": "chain_of_thought_chainofthought_reason_custom", "callee": "append", "source_file": "modules\\shadow\\chain_of_thought.py", "source_location": "L157"}, {"caller_nid": "chain_of_thought_chainofthought_reason_custom", "callee": "enumerate", "source_file": "modules\\shadow\\chain_of_thought.py", "source_location": "L161"}, {"caller_nid": "chain_of_thought_chainofthought_reason_custom", "callee": "append", "source_file": "modules\\shadow\\chain_of_thought.py", "source_location": "L162"}, {"caller_nid": "chain_of_thought_chainofthought_reason_custom", "callee": "get", "source_file": "modules\\shadow\\chain_of_thought.py", "source_location": "L164"}, {"caller_nid": "chain_of_thought_chainofthought_estimate_complexity", "callee": "split", "source_file": "modules\\shadow\\chain_of_thought.py", "source_location": "L181"}, {"caller_nid": "chain_of_thought_chainofthought_estimate_complexity", "callee": "len", "source_file": "modules\\shadow\\chain_of_thought.py", "source_location": "L182"}, {"caller_nid": "chain_of_thought_chainofthought_estimate_complexity", "callee": "lower", "source_file": "modules\\shadow\\chain_of_thought.py", "source_location": "L183"}, {"caller_nid": "chain_of_thought_chainofthought_estimate_complexity", "callee": "any", "source_file": "modules\\shadow\\chain_of_thought.py", "source_location": "L187"}, {"caller_nid": "chain_of_thought_chainofthought_estimate_complexity", "callee": "any", "source_file": "modules\\shadow\\chain_of_thought.py", "source_location": "L188"}, {"caller_nid": "chain_of_thought_chainofthought_estimate_complexity", "callee": "any", "source_file": "modules\\shadow\\chain_of_thought.py", "source_location": "L196"}, {"caller_nid": "chain_of_thought_chainofthought_estimate_complexity", "callee": "any", "source_file": "modules\\shadow\\chain_of_thought.py", "source_location": "L199"}, {"caller_nid": "chain_of_thought_chainofthought_get_reasoning_stats", "callee": "sum", "source_file": "modules\\shadow\\chain_of_thought.py", "source_location": "L220"}, {"caller_nid": "chain_of_thought_chainofthought_get_reasoning_stats", "callee": "sum", "source_file": "modules\\shadow\\chain_of_thought.py", "source_location": "L221"}, {"caller_nid": "chain_of_thought_chainofthought_get_reasoning_stats", "callee": "sum", "source_file": "modules\\shadow\\chain_of_thought.py", "source_location": "L222"}, {"caller_nid": "chain_of_thought_chainofthought_get_reasoning_stats", "callee": "len", "source_file": "modules\\shadow\\chain_of_thought.py", "source_location": "L234"}, {"caller_nid": "chain_of_thought_chainofthought_get_reasoning_stats", "callee": "len", "source_file": "modules\\shadow\\chain_of_thought.py", "source_location": "L240"}, {"caller_nid": "chain_of_thought_chainofthought_get_reasoning_stats", "callee": "len", "source_file": "modules\\shadow\\chain_of_thought.py", "source_location": "L242"}, {"caller_nid": "chain_of_thought_chainofthought_execute_pipeline", "callee": "time", "source_file": "modules\\shadow\\chain_of_thought.py", "source_location": "L375"}, {"caller_nid": "chain_of_thought_chainofthought_execute_pipeline", "callee": "time", "source_file": "modules\\shadow\\chain_of_thought.py", "source_location": "L379"}, {"caller_nid": "chain_of_thought_chainofthought_execute_pipeline", "callee": "replace", "source_file": "modules\\shadow\\chain_of_thought.py", "source_location": "L384"}, {"caller_nid": "chain_of_thought_chainofthought_execute_pipeline", "callee": "replace", "source_file": "modules\\shadow\\chain_of_thought.py", "source_location": "L386"}, {"caller_nid": "chain_of_thought_chainofthought_execute_pipeline", "callee": "replace", "source_file": "modules\\shadow\\chain_of_thought.py", "source_location": "L388"}, {"caller_nid": "chain_of_thought_chainofthought_execute_pipeline", "callee": "get", "source_file": "modules\\shadow\\chain_of_thought.py", "source_location": "L388"}, {"caller_nid": "chain_of_thought_chainofthought_execute_pipeline", "callee": "_generate_fn", "source_file": "modules\\shadow\\chain_of_thought.py", "source_location": "L392"}, {"caller_nid": "chain_of_thought_chainofthought_execute_pipeline", "callee": "error", "source_file": "modules\\shadow\\chain_of_thought.py", "source_location": "L394"}, {"caller_nid": "chain_of_thought_chainofthought_execute_pipeline", "callee": "time", "source_file": "modules\\shadow\\chain_of_thought.py", "source_location": "L401"}, {"caller_nid": "chain_of_thought_chainofthought_execute_pipeline", "callee": "append", "source_file": "modules\\shadow\\chain_of_thought.py", "source_location": "L411"}, {"caller_nid": "chain_of_thought_chainofthought_execute_pipeline", "callee": "time", "source_file": "modules\\shadow\\chain_of_thought.py", "source_location": "L414"}, {"caller_nid": "chain_of_thought_chainofthought_execute_pipeline", "callee": "score", "source_file": "modules\\shadow\\chain_of_thought.py", "source_location": "L420"}, {"caller_nid": "chain_of_thought_chainofthought_execute_pipeline", "callee": "warning", "source_file": "modules\\shadow\\chain_of_thought.py", "source_location": "L422"}, {"caller_nid": "chain_of_thought_chainofthought_execute_pipeline", "callee": "append", "source_file": "modules\\shadow\\chain_of_thought.py", "source_location": "L433"}, {"caller_nid": "chain_of_thought_chainofthought_execute_pipeline", "callee": "info", "source_file": "modules\\shadow\\chain_of_thought.py", "source_location": "L442"}, {"caller_nid": "chain_of_thought_chainofthought_execute_pipeline", "callee": "time", "source_file": "modules\\shadow\\chain_of_thought.py", "source_location": "L453"}, {"caller_nid": "chain_of_thought_chainofthought_execute_pipeline", "callee": "len", "source_file": "modules\\shadow\\chain_of_thought.py", "source_location": "L454"}, {"caller_nid": "chain_of_thought_chainofthought_execute_pipeline", "callee": "append", "source_file": "modules\\shadow\\chain_of_thought.py", "source_location": "L458"}, {"caller_nid": "chain_of_thought_estimate_tokens", "callee": "max", "source_file": "modules\\shadow\\chain_of_thought.py", "source_location": "L464"}, {"caller_nid": "chain_of_thought_estimate_tokens", "callee": "len", "source_file": "modules\\shadow\\chain_of_thought.py", "source_location": "L464"}]}